CHANGES.rst
CONTRIBUTORS.rst
LICENSE.rst
MANIFEST.in
README.rst
setup.cfg
setup.py
docs/conf.py
docs/index.rst
src/collective/__init__.py
src/collective.googlecloudlogging.egg-info/PKG-INFO
src/collective.googlecloudlogging.egg-info/SOURCES.txt
src/collective.googlecloudlogging.egg-info/dependency_links.txt
src/collective.googlecloudlogging.egg-info/entry_points.txt
src/collective.googlecloudlogging.egg-info/namespace_packages.txt
src/collective.googlecloudlogging.egg-info/not-zip-safe
src/collective.googlecloudlogging.egg-info/requires.txt
src/collective.googlecloudlogging.egg-info/top_level.txt
src/collective/googlecloudlogging/__init__.py