Metadata-Version: 1.2
Name: collective.googlecloudlogging
Version: 1.0
Summary: Google Cloud Logging Integration
Home-page: https://github.com/collective/collective.googlecloudlogging
Author: Peter Holzer
Author-email: peter.holzer@agitator.com
License: GPL version 2
Project-URL: PyPI, https://pypi.python.org/pypi/collective.googlecloudlogging
Project-URL: Source, https://github.com/collective/collective.googlecloudlogging
Project-URL: Tracker, https://github.com/collective/collective.googlecloudlogging/issues
Keywords: Python Plone CMS
Platform: UNKNOWN
Classifier: Environment :: Web Environment
Classifier: Framework :: Plone
Classifier: Framework :: Plone :: Addon
Classifier: Framework :: Plone :: 5.2
Classifier: Programming Language :: Python
Classifier: Programming Language :: Python :: 3.7
Classifier: Programming Language :: Python :: 3.8
Classifier: Operating System :: OS Independent
Classifier: License :: OSI Approved :: GNU General Public License v2 (GPLv2)
Requires-Python: >=3.7
